Metadata-Version: 1.1
Name: Krdc
Version: 0.0.1
Summary: Still working on...
Home-page: UNKNOWN
Author: Hiwa Hossien
Author-email: hiwahokin@gmail.com
License: MIT
Keywords: Coming soon
Platform: UNKNOWN
Classifier: Development Status :: 5 - Production/Stable
Classifier: Intended Audience :: Education
Classifier: Operating System :: Microsoft :: Windows :: Windows 10
Classifier: License :: OSI Approved :: MIT License
Classifier: Programming Language :: Python :: 3
